rfwtools/__init__.py
rfwtools/config.py
rfwtools/data_set.py
rfwtools/example.py
rfwtools/example_set.py
rfwtools/example_validator.py
rfwtools/feature_set.py
rfwtools/mya.py
rfwtools/network.py
rfwtools/timestamp.py
rfwtools/utils.py
rfwtools/dim_reduction/__init__.py
rfwtools/dim_reduction/pca.py
rfwtools/dim_reduction/tsne.py
rfwtools/extractor/__init__.py
rfwtools/extractor/autoregressive.py
rfwtools/extractor/down_sample.py
rfwtools/extractor/tsf.py
rfwtools/extractor/utils.py
rfwtools/extractor/windowing.py
rfwtools/visualize/__init__.py
rfwtools/visualize/heatmap.py
rfwtools/visualize/scatterplot.py
rfwtools/visualize/timeline.py
rfwtools-1.3.0.dist-info/LICENSE
rfwtools-1.3.0.dist-info/METADATA
rfwtools-1.3.0.dist-info/WHEEL
rfwtools-1.3.0.dist-info/top_level.txt
rfwtools-1.3.0.dist-info/RECORD
