Metadata-Version: 2.1
Name: rfwtools
Version: 1.3.0
Summary: A package for working with CEBAF's C100 RF harvester waveforms
Home-page: https://github.com/JeffersonLab/rfwtools
Author: Adam Carpenter, Jefferson Lab
Author-email: adamc@jlab.org
License: JLab
Classifier: Programming Language :: Python :: 3
Classifier: Operating System :: Microsoft :: Windows
Classifier: Operating System :: POSIX :: Linux
Requires-Python: >=3.7
License-File: LICENSE
Requires-Dist: matplotlib
Requires-Dist: numpy
Requires-Dist: pandas
Requires-Dist: requests
Requires-Dist: scipy
Requires-Dist: statsmodels
Requires-Dist: tzlocal
Requires-Dist: PyYAML
Requires-Dist: seaborn
Requires-Dist: scikit-learn
Requires-Dist: tqdm
Requires-Dist: tsfresh
Requires-Dist: lttb
Provides-Extra: dev
Requires-Dist: sphinx-rtd-theme ; extra == 'dev'
